django_choices_enums
