Metadata-Version: 1.2
Name: django-choices-enums
Version: 1.0.1
Summary: The enum type used for Django choices enables Django's choices to support code prompts!!
Home-page: https://github.com/gojuukaze/django-choices-enum
Author: gojuukaze
Author-email: ikaze_email@163.com
License: UNKNOWN
Platform: Any
Classifier: Development Status :: 5 - Production/Stable
Classifier: Intended Audience :: Developers
Classifier: License :: OSI Approved :: GNU General Public License v3 (GPLv3)
Classifier: Operating System :: OS Independent
Classifier: Framework :: Django
Classifier: Programming Language :: Python :: 3.4
Classifier: Programming Language :: Python :: 3.5
Classifier: Programming Language :: Python :: 3.6
Classifier: Programming Language :: Python :: 3.7
Requires-Python: >=3
